twwanim/TriGraph.py
twwanim/TwinwidthAnimation.py
twwanim/__init__.py
twwanim/twwanim.py
twwanim/data/ContractAction.py
twwanim/data/TriGraphData.py
twwanim/data/__init__.py
twwanim/readwrite/__init__.py
twwanim/readwrite/contraction.py
twwanim/readwrite/pace.py
twwanim-0.0.2.dist-info/LICENSE
twwanim-0.0.2.dist-info/METADATA
twwanim-0.0.2.dist-info/WHEEL
twwanim-0.0.2.dist-info/entry_points.txt
twwanim-0.0.2.dist-info/top_level.txt
twwanim-0.0.2.dist-info/RECORD
