Metadata-Version: 2.1
Name: twwanim
Version: 0.0.2
Summary: Twin-width animation tools.
Home-page: https://github.com/mogproject/twwanim
Author: Yosuke Mizutani
Author-email: mogproj@gmail.com
License: Apache 2.0 License
License-File: LICENSE
Requires-Dist: networkx >=3.1
Requires-Dist: manim >=0.18.0
